grpc_status/__init__.py
grpc_status/_async.py
grpc_status/_common.py
grpc_status/rpc_status.py
grpcio_status-1.75.0.dist-info/LICENSE
grpcio_status-1.75.0.dist-info/METADATA
grpcio_status-1.75.0.dist-info/WHEEL
grpcio_status-1.75.0.dist-info/top_level.txt
grpcio_status-1.75.0.dist-info/RECORD
